domino_cli/__init__.py
domino_cli/__main__.py
domino_cli/installer_config.py
domino_cli/core/ApplicationContext.py
domino_cli/core/__init__.py
domino_cli/core/cli/CLI.py
domino_cli/core/cli/Logging.py
domino_cli/core/cli/RuntimeHelper.py
domino_cli/core/cli/__init__.py
domino_cli/core/client/DominoClient.py
domino_cli/core/client/OAuthAuthorizationClient.py
domino_cli/core/client/__init__.py
domino_cli/core/command/AbstractCommand.py
domino_cli/core/command/AbstractLifecycleCommand.py
domino_cli/core/command/AuthCommand.py
domino_cli/core/command/DeployApplicationCommand.py
domino_cli/core/command/ExitCommand.py
domino_cli/core/command/HelpCommand.py
domino_cli/core/command/ImportCommand.py
domino_cli/core/command/InfoCommand.py
domino_cli/core/command/RestartApplicationCommand.py
domino_cli/core/command/SecretCommand.py
domino_cli/core/command/StartApplicationCommand.py
domino_cli/core/command/StopApplicationCommand.py
domino_cli/core/command/WizardCommand.py
domino_cli/core/command/__init__.py
domino_cli/core/command/dsl/__init__.py
domino_cli/core/command/dsl/dsm/DSLCreate.py
domino_cli/core/command/dsl/dsm/DSLDelete.py
domino_cli/core/command/dsl/dsm/DSLLocking.py
domino_cli/core/command/dsl/dsm/DSLMain.py
domino_cli/core/command/dsl/dsm/DSLMetadata.py
domino_cli/core/command/dsl/dsm/DSLRetrieval.py
domino_cli/core/command/dsl/dsm/__init__.py
domino_cli/core/domain/AuthMode.py
domino_cli/core/domain/AuthRequest.py
domino_cli/core/domain/CommandDescriptor.py
domino_cli/core/domain/DominoCommand.py
domino_cli/core/domain/DominoRequest.py
domino_cli/core/domain/HTTPMethod.py
domino_cli/core/domain/OAuthConfig.py
domino_cli/core/domain/SessionContext.py
domino_cli/core/domain/__init__.py
domino_cli/core/service/AuthenticationService.py
domino_cli/core/service/CommandProcessor.py
domino_cli/core/service/ConfigurationWizardService.py
domino_cli/core/service/DominoService.py
domino_cli/core/service/SecretService.py
domino_cli/core/service/SessionContextHolder.py
domino_cli-2.4.0.dist-info/METADATA
domino_cli-2.4.0.dist-info/WHEEL
domino_cli-2.4.0.dist-info/entry_points.txt
domino_cli-2.4.0.dist-info/RECORD
