Metadata-Version: 2.4
Name: domino-cli
Version: 2.4.0
Summary: Domino Platform CLI tool, providing utilities to install, configure and control your Domino Platform insfrastructure
Project-URL: Maintainer's website, https://psprog.hu
Classifier: Development Status :: 5 - Production/Stable
Classifier: Environment :: Console
Classifier: Intended Audience :: Developers
Classifier: Intended Audience :: System Administrators
Classifier: Natural Language :: English
Classifier: Operating System :: Microsoft :: Windows
Classifier: Operating System :: POSIX :: Linux
Requires-Python: >=3.8
Requires-Dist: bcrypt==4.0.0
Requires-Dist: pyyaml
Requires-Dist: requests
